Metadata-Version: 2.1
Name: torchhaarfeatures
Version: 0.0.2
Summary: Haar-like features using PyTorch
Home-page: http://github.com/masadcv/PyTorchHaarFeatures
Author: Muhammad Asad
Author-email: muhammad.asad@kcl.ac.uk
License: BSD-3-Clause
Keywords: haar-like 2d 3d medical features hand-crafted
Platform: UNKNOWN
Classifier: Operating System :: OS Independent
Classifier: License :: OSI Approved :: BSD License
Classifier: Programming Language :: Python :: 3
